ailoy/_core.pyd
ailoy/_core.pyi
ailoy/_patches.py
ailoy/__init__.py
ailoy_py-0.2.5.dist-info/DELVEWHEEL
ailoy_py-0.2.5.dist-info/entry_points.txt
ailoy_py-0.2.5.dist-info/METADATA
ailoy_py-0.2.5.dist-info/RECORD
ailoy_py-0.2.5.dist-info/WHEEL
ailoy_py.libs/faiss-70e72914673af523d222196bb9e6c0b2.dll
ailoy_py.libs/libblas-72618be97949cccd20a1b09ef3c6eec6.dll
ailoy_py.libs/libgcc_s_seh-1-b29205fd654325fed69362a1148917b8.dll
ailoy_py.libs/libgfortran-5-032c771c8b6ad8b5cfc4ee1764df4a5f.dll
ailoy_py.libs/liblapack-41b205a28528a3f280b22e473955a4dc.dll
ailoy_py.libs/libquadmath-0-d2e90a515190680e56a6e9592a704416.dll
ailoy_py.libs/libwinpthread-1-df3b318b0ccea9a3204a7f9f31025720.dll
ailoy_py.libs/msvcp140-2a7008da6f9aae43c7a434835dcaf31e.dll
ailoy_py.libs/tvm_ffi-f045038f81caaf371c9e2fab0c40181e.dll
ailoy_py.libs/tvm_runtime-73e27318a65b3863f6349186e4ba7e16.dll
ailoy_py.libs/vcomp140-55aba23cdcd6484fbb06f4155b8ca75a.dll
