Metadata-Version: 2.4
Name: ailoy-py
Version: 0.2.5
Classifier: Development Status :: 3 - Alpha
Classifier: Intended Audience :: Developers
Classifier: Topic :: Scientific/Engineering :: Artificial Intelligence
Classifier: Topic :: Software Development :: Libraries :: Python Modules
Classifier: Programming Language :: Rust
Classifier: Programming Language :: Python :: 3
Classifier: Programming Language :: Python :: 3.10
Classifier: Programming Language :: Python :: 3.11
Classifier: Programming Language :: Python :: 3.12
Classifier: Programming Language :: Python :: 3.13
Classifier: Programming Language :: Python :: 3.14
Classifier: Programming Language :: Python :: Implementation :: CPython
Summary: A lightweight library for building AI applications
Author-email: "Brekkylab Inc." <contact@brekkylab.com>
License-Expression: Apache-2.0
Requires-Python: >=3.10
Project-URL: Documentation, https://brekkylab.github.io/ailoy
Project-URL: Homepage, https://brekkylab.github.io/ailoy
Project-URL: Issues, https://github.com/brekkylab/ailoy/issues
Project-URL: Repository, https://github.com/brekkylab/ailoy
